opentelemetry/instrumentation/asgi/__init__.py
opentelemetry/instrumentation/asgi/package.py
opentelemetry/instrumentation/asgi/version.py
opentelemetry_instrumentation_asgi-0.33b0.dist-info/METADATA
opentelemetry_instrumentation_asgi-0.33b0.dist-info/WHEEL
opentelemetry_instrumentation_asgi-0.33b0.dist-info/top_level.txt
opentelemetry_instrumentation_asgi-0.33b0.dist-info/RECORD
